arithtools/__init__.py
arith_tools-1.0.0.dist-info/LICENSE
arith_tools-1.0.0.dist-info/METADATA
arith_tools-1.0.0.dist-info/WHEEL
arith_tools-1.0.0.dist-info/top_level.txt
arith_tools-1.0.0.dist-info/RECORD
