Metadata-Version: 2.1
Name: arith-tools
Version: 1.0.0
Summary: Use all the simple arithmetic calculations such as fibonacci series, armstrong number etc.
Home-page: https://github.com/SoumadeepChoudhury/arith-tools
Author: Ahens | An Initiative to Initial (Soumadeep Choudhury)
Author-email: ahensinitiative@gmail.com
License: MIT
Keywords: python,arithmetic,tools,arith-tools,arithmetic operations,Math,python3,pip,pip3,fibonacci,armstrong,boiled-egg
Platform: UNKNOWN
Classifier: Development Status :: 5 - Production/Stable
Classifier: Intended Audience :: Developers
Classifier: License :: OSI Approved :: MIT License
Classifier: Programming Language :: Python :: 3
Classifier: Programming Language :: Python :: 3.7
Classifier: Operating System :: Unix
Classifier: Operating System :: MacOS :: MacOS X
Classifier: Operating System :: Microsoft :: Windows
License-File: LICENSE
